luisy/__init__.py
luisy/__main__.py
luisy/cli.py
luisy/code_inspection.py
luisy/config.py
luisy/decorators.py
luisy/default_params.py
luisy/file_system.py
luisy/hashes.py
luisy/helpers.py
luisy/luigi_interface.py
luisy/targets.py
luisy/testing.py
luisy/visualize.py
luisy/tasks/__init__.py
luisy/tasks/base.py
luisy-1.4.7.dist-info/LICENSE.txt
luisy-1.4.7.dist-info/METADATA
luisy-1.4.7.dist-info/WHEEL
luisy-1.4.7.dist-info/entry_points.txt
luisy-1.4.7.dist-info/top_level.txt
luisy-1.4.7.dist-info/RECORD
