Metadata-Version: 2.1
Name: luisy
Version: 1.4.7
Summary: Framework to build data pipelines
Author: Robert Bosch GmbH
License: Apache-2.0
License-File: LICENSE.txt
Requires-Dist: azure-storage-blob>=12.6.0
Requires-Dist: luigi>=3.0.0
Requires-Dist: pandas>=1.0.4
Requires-Dist: tables>=3.6.1
Requires-Dist: networkx
Requires-Dist: pipdeptree>=2.2.1
Requires-Dist: requirements-parser==0.5.0
Requires-Dist: distlib>=0.3.4
Requires-Dist: matplotlib>=3.3.0
Requires-Dist: numpy
Requires-Dist: pyarrow
Requires-Dist: pyspark
Provides-Extra: dev
Requires-Dist: check-manifest; extra == "dev"
Provides-Extra: test
Requires-Dist: coverage; extra == "test"
